baseweb/__init__.py
baseweb/util.py
baseweb/static/__init__.py
baseweb/static/css/__init__.py
baseweb/static/css/main.css
baseweb/static/css/process_diagram.css
baseweb/static/js/__init__.py
baseweb/static/js/app.js
baseweb/static/js/common.js
baseweb/static/js/router.js
baseweb/static/js/socketio.js
baseweb/static/js/components/CollectionView.js
baseweb/static/js/components/LineChart.js
baseweb/static/js/components/NavigationDrawer.js
baseweb/static/js/components/Page.js
baseweb/static/js/components/PageWithBanner.js
baseweb/static/js/components/PageWithStatus.js
baseweb/static/js/components/ProcessDiagram.js
baseweb/static/js/components/__init__.py
baseweb/static/vendor/__init__.py
baseweb/static/vendor/css/__init__.py
baseweb/static/vendor/css/bootstrap-datetimepicker.css
baseweb/static/vendor/css/highlight.js.github.css
baseweb/static/vendor/css/roboto-material-icons.css
baseweb/static/vendor/css/vfg.css
baseweb/static/vendor/css/vue-multiselect.min.css
baseweb/static/vendor/css/vuetify.min.css
baseweb/static/vendor/fonts/KFOlCnqEu92Fr1MmEU9fBBc9.ttf
baseweb/static/vendor/fonts/KFOlCnqEu92Fr1MmSU5fBBc9.ttf
baseweb/static/vendor/fonts/KFOlCnqEu92Fr1MmWUlfBBc9.ttf
baseweb/static/vendor/fonts/KFOmCnqEu92Fr1Mu4mxP.ttf
baseweb/static/vendor/fonts/__init__.py
baseweb/static/vendor/fonts/flUhRq6tzZclQEJ-Vdg-IuiaDsNcIhQ8tQ.woff2
baseweb/static/vendor/js/Chart.min.js
baseweb/static/vendor/js/__init__.py
baseweb/static/vendor/js/bootstrap-datetimepicker.min.js
baseweb/static/vendor/js/bootstrap.min.js
baseweb/static/vendor/js/highlight.min.js
baseweb/static/vendor/js/html5shiv.min.js
baseweb/static/vendor/js/index.js.map
baseweb/static/vendor/js/jquery.min.js
baseweb/static/vendor/js/moment.min.js
baseweb/static/vendor/js/respond.min.js
baseweb/static/vendor/js/socket.io.min.js.map
baseweb/static/vendor/js/socket.io.slim.js
baseweb/static/vendor/js/vue-chartjs.min.js
baseweb/static/vendor/js/vue-chartjs.min.js.map
baseweb/static/vendor/js/vue-form-generator.min.js
baseweb-0.4.3.dist-info/licenses/LICENSE.txt
baseweb-0.4.3.dist-info/METADATA
baseweb-0.4.3.dist-info/WHEEL
baseweb-0.4.3.dist-info/top_level.txt
baseweb-0.4.3.dist-info/RECORD
