Metadata-Version: 2.4
Name: baseweb
Version: 0.4.3
Summary: A Pythonic base for building interactive web applications
Home-page: https://github.com/christophevg/baseweb
Author: Christophe VG
License: MIT
Keywords: Flask Vue REST SocketIO
Classifier: Programming Language :: Python :: 3.9
Classifier: Programming Language :: Python :: 3.10
Classifier: Programming Language :: Python :: 3.11
Classifier: Programming Language :: Python :: 3.12
Classifier: Environment :: Web Environment
Classifier: Intended Audience :: Developers
Classifier: Topic :: Software Development :: Libraries :: Python Modules
Classifier: License :: OSI Approved :: MIT License
Classifier: Development Status :: 4 - Beta
License-File: LICENSE.txt
Requires-Dist: Flask
Requires-Dist: Flask-RESTful
Requires-Dist: Flask-SocketIO
Requires-Dist: python-dotenv
Requires-Dist: websocket-client
Requires-Dist: python-engineio
Requires-Dist: python-socketio
Requires-Dist: dotmap
Requires-Dist: pyfiglet
Requires-Dist: python-slugify
Requires-Dist: tabulate
Dynamic: author
Dynamic: classifier
Dynamic: description
Dynamic: description-content-type
Dynamic: home-page
Dynamic: keywords
Dynamic: license
Dynamic: license-file
Dynamic: requires-dist
Dynamic: summary
